[{"serie": "Teammates", "value": 15, "category": "Gyalis"}, {"serie": "Teammates", "value": 15, "category": "Kinu"}, {"serie": "Teammates", "value": 14, "category": "Pigepic"}, {"serie": "Teammates", "value": 9, "category": "Ukama"}, {"serie": "Teammates", "value": 8, "category": "Wiplump"}, {"serie": "Teammates", "value": 7, "category": "Valash"}, {"serie": "Teammates", "value": 7, "category": "Tuvine"}, {"serie": "Teammates", "value": 6, "category": "Vulcrane"}, {"serie": "Teammates", "value": 5, "category": "Mushook"}, {"serie": "Teammates", "value": 4, "category": "Kalabyss"}, {"serie": "Teammates", "value": 4, "category": "Raize"}, {"serie": "Teammates", "value": 3, "category": "Saipat"}, {"serie": "Teammates", "value": 2, "category": "Myx"}, {"serie": "Teammates", "value": 2, "category": "Mastione"}, {"serie": "Teammates", "value": 2, "category": "Granpah"}, {"serie": "Teammates", "value": 2, "category": "Tateru"}, {"serie": "Teammates", "value": 2, "category": "Raican"}, {"serie": "Teammates", "value": 1, "category": "Anahir"}, {"serie": "Teammates", "value": 1, "category": "Cerneaf"}, {"serie": "Teammates", "value": 1, "category": "Gazuma"}, {"serie": "Teammates", "value": 1, "category": "Nidrasil"}, {"serie": "Teammates", "value": 1, "category": "Mudrid"}]