[{"serie": "Temtems", "value": 1.92, "category": "Crystal"}, {"serie": "Temtems", "value": 0.46, "category": "Earth"}, {"serie": "Temtems", "value": 0.04, "category": "Electric"}, {"serie": "Temtems", "value": 0.79, "category": "Fire"}, {"serie": "Temtems", "value": 1.50, "category": "Melee"}, {"serie": "Temtems", "value": 1.00, "category": "Mental"}, {"serie": "Temtems", "value": 1.21, "category": "Nature"}, {"serie": "Temtems", "value": 0.46, "category": "Neutral"}, {"serie": "Temtems", "value": 1.96, "category": "Toxic"}, {"serie": "Temtems", "value": 1.58, "category": "Water"}, {"serie": "Temtems", "value": 3.08, "category": "Wind"}]